arenarobot/__init__.py
arenarobot/_version.py
arenarobot/occupancy_grid/__init__.py
arenarobot/occupancy_grid/const.py
arenarobot/scripts/__init__.py
arenarobot/scripts/arena_robot_service.py
arenarobot/service/__init__.py
arenarobot/service/service.py
arenarobot/service/controller/__init__.py
arenarobot/service/controller/pololu_slave_i2c.py
arenarobot/service/processor/__init__.py
arenarobot/service/processor/apriltag_detector.py
arenarobot/service/processor/t265.py
arenarobot/service/sensor/__init__.py
arenarobot/service/sensor/beluga_serial.py
arenarobot/service/sensor/licosa_serial.py
arenarobot/service/sensor/t265.py
arenarobot/service/sensor/vl53l5cx.py
arenavideocall/__init__.py
arenavideocall/scripts/__init__.py
arenavideocall/scripts/arena_video_call_chrome.py
licosa_py/__init__.py
licosa_py/packets.py
licosa_py/parser.py
licosa_py/transformer.py
vl53l5cx_py/__init__.py
vl53l5cx_py/driver.cpython-38-darwin.so
vl53l5cx_py/helpers.py
arena_robot-2.2.0.dist-info/LICENSE
arena_robot-2.2.0.dist-info/METADATA
arena_robot-2.2.0.dist-info/WHEEL
arena_robot-2.2.0.dist-info/entry_points.txt
arena_robot-2.2.0.dist-info/top_level.txt
arena_robot-2.2.0.dist-info/RECORD
