Metadata-Version: 2.1
Name: arena-robot
Version: 2.2.0
Summary: Robot integration runtime for the ARENA
Home-page: https://github.com/arenaxr/arena-robot
Author: Conix Research Center
Author-email: info@conix.io
License: BSD-3-Clause
Project-URL: Bug Reports, https://github.com/arenaxr/arena-robot/issues
Project-URL: Source, https://github.com/arenaxr/arena-robot
Keywords: arena robot ar vr robotics drone lidar vl53l5cx stm selenium jitsi video videocall conference
Platform: any
Classifier: Development Status :: 4 - Beta
Classifier: Framework :: Robot Framework
Classifier: Intended Audience :: Developers
Classifier: Intended Audience :: Education
Classifier: Intended Audience :: Science/Research
Classifier: Intended Audience :: Telecommunications Industry
Classifier: License :: OSI Approved :: BSD License
Classifier: Programming Language :: C
Classifier: Programming Language :: Cython
Classifier: Programming Language :: Python :: 3
Classifier: Programming Language :: Python :: 3 :: Only
Classifier: Topic :: Scientific/Engineering
Classifier: Topic :: System :: Distributed Computing
Classifier: Topic :: System :: Hardware
Requires-Python: >=3.8, <4
License-File: LICENSE
Requires-Dist: aioserial (<2,>=1)
Requires-Dist: arena-py (<1,>=0.1.43)
Requires-Dist: scipy (>=1.8)
Requires-Dist: numpy (<2,>=1)
Requires-Dist: pyserial (<4,>=3)
Requires-Dist: python-periphery (<3,>=2)
Requires-Dist: selenium (<4,>=3)
Requires-Dist: setuptools-scm (>=6.0)
Requires-Dist: slam3d (<1,>=0)
Requires-Dist: transformations (==2021.6.6)
Provides-Extra: apriltag_detector
Requires-Dist: dt-apriltags (<4,>=3) ; extra == 'apriltag_detector'
Requires-Dist: opencv-python (==4.5.5.64) ; extra == 'apriltag_detector'
Provides-Extra: dev
Requires-Dist: bandit (<2,>=1) ; extra == 'dev'
Requires-Dist: flake8 (<4,>=3) ; extra == 'dev'
Requires-Dist: flake8-bugbear (<22,>=21) ; extra == 'dev'
Requires-Dist: isort (<6,>=5) ; extra == 'dev'
Requires-Dist: pydocstyle (<7,>=6) ; extra == 'dev'
Requires-Dist: pylint (<3,>=2) ; extra == 'dev'
Provides-Extra: realsense
Requires-Dist: pyrealsense2 (<3,>=2) ; extra == 'realsense'
